gradient/__init__.py
gradient/_base_client.py
gradient/_client.py
gradient/_compat.py
gradient/_constants.py
gradient/_exceptions.py
gradient/_files.py
gradient/_models.py
gradient/_qs.py
gradient/_resource.py
gradient/_response.py
gradient/_streaming.py
gradient/_types.py
gradient/_version.py
gradient/py.typed
gradient/_utils/__init__.py
gradient/_utils/_compat.py
gradient/_utils/_datetime_parse.py
gradient/_utils/_logs.py
gradient/_utils/_proxy.py
gradient/_utils/_reflection.py
gradient/_utils/_resources_proxy.py
gradient/_utils/_streams.py
gradient/_utils/_sync.py
gradient/_utils/_transform.py
gradient/_utils/_typing.py
gradient/_utils/_utils.py
gradient/lib/.keep
gradient/resources/__init__.py
gradient/resources/images.py
gradient/resources/regions.py
gradient/resources/retrieve.py
gradient/resources/agents/__init__.py
gradient/resources/agents/agents.py
gradient/resources/agents/api_keys.py
gradient/resources/agents/evaluation_datasets.py
gradient/resources/agents/evaluation_runs.py
gradient/resources/agents/evaluation_test_cases.py
gradient/resources/agents/functions.py
gradient/resources/agents/knowledge_bases.py
gradient/resources/agents/routes.py
gradient/resources/agents/versions.py
gradient/resources/agents/chat/__init__.py
gradient/resources/agents/chat/chat.py
gradient/resources/agents/chat/completions.py
gradient/resources/agents/evaluation_metrics/__init__.py
gradient/resources/agents/evaluation_metrics/evaluation_metrics.py
gradient/resources/agents/evaluation_metrics/scheduled_indexing.py
gradient/resources/agents/evaluation_metrics/anthropic/__init__.py
gradient/resources/agents/evaluation_metrics/anthropic/anthropic.py
gradient/resources/agents/evaluation_metrics/anthropic/keys.py
gradient/resources/agents/evaluation_metrics/oauth2/__init__.py
gradient/resources/agents/evaluation_metrics/oauth2/dropbox.py
gradient/resources/agents/evaluation_metrics/oauth2/oauth2.py
gradient/resources/agents/evaluation_metrics/openai/__init__.py
gradient-3.10.0.dist-info/METADATA
gradient-3.10.0.dist-info/WHEEL
gradient-3.10.0.dist-info/licenses/LICENSE
gradient-3.10.0.dist-info/RECORD
